README.md
setup.py
picogeojson/__init__.py
picogeojson/antimeridian.py
picogeojson/bbox.py
picogeojson/crs.py
picogeojson/deserializer.py
picogeojson/docstrings.py
picogeojson/identity.py
picogeojson/map.py
picogeojson/orientation.py
picogeojson/serializer.py
picogeojson/transformations.py
picogeojson/types.py
picogeojson/validators.py
picogeojson.egg-info/PKG-INFO
picogeojson.egg-info/SOURCES.txt
picogeojson.egg-info/dependency_links.txt
picogeojson.egg-info/requires.txt
picogeojson.egg-info/top_level.txt