Metadata-Version: 1.1
Name: picogeojson
Version: 0.8.0
Summary: RFC-7946 compliant GeoJSON parser and emitter
Home-page: UNKNOWN
Author: Nat Wilson
Author-email: natw@fortyninemaps.com
License: MIT
Keywords: minimal geojson
Platform: UNKNOWN
Classifier: Development Status :: 5 - Production/Stable
Classifier: Topic :: Scientific/Engineering :: GIS
Classifier: Intended Audience :: Developers
Classifier: License :: OSI Approved :: MIT License
Classifier: Programming Language :: Python :: 2
Classifier: Programming Language :: Python :: 2.7
Classifier: Programming Language :: Python :: 3
Classifier: Programming Language :: Python :: 3.3
Classifier: Programming Language :: Python :: 3.4
Classifier: Programming Language :: Python :: 3.5
Classifier: Programming Language :: Python :: 3.6
